splitAxes/__init__.py
splitAxes/multiAxes.py
splitAxes/__pycache__/__init__.cpython-311.pyc
splitAxes/__pycache__/multiAxes.cpython-311.pyc
splitAxes/gridder/__init__.py
splitAxes/gridder/gridder.py
splitAxes/gridder/__pycache__/__init__.cpython-311.pyc
splitAxes/gridder/__pycache__/gridder.cpython-311.pyc
splitAxes-0.9.2.dist-info/LICENSE
splitAxes-0.9.2.dist-info/METADATA
splitAxes-0.9.2.dist-info/WHEEL
splitAxes-0.9.2.dist-info/top_level.txt
splitAxes-0.9.2.dist-info/RECORD
