Metadata-Version: 2.1
Name: splitAxes
Version: 0.9.2
Summary: A split module for easily generating matplotlib figures with split x axes
Author-email: "Thomas M. Boudreaux" <thomas@boudreauxmail.com>, "Keighley E. Rockcliffe" <keighrockcliffe@gmail.com>
License: Copyright 2023 Thomas M. Boudreaux
Project-URL: Homepage, https://github.com/tboudreaux/splitAxes
Keywords: graphing
Classifier: Development Status :: 4 - Beta
Classifier: Intended Audience :: Science/Research
Classifier: License :: OSI Approved :: MIT License
Classifier: Programming Language :: Python
Classifier: Programming Language :: Python :: 3
Requires-Python: >=3.8
License-File: LICENSE
Requires-Dist: matplotlib
Requires-Dist: numpy
